mmdet3d/__init__.py
mmdet3d/registry.py
mmdet3d/version.py
mmdet3d/.mim/dataset-index.yml
mmdet3d/.mim/model-index.yml
mmdet3d/.mim/configs/3dssd/3dssd_4xb4_kitti-3d-car.py
mmdet3d/.mim/configs/3dssd/metafile.yml
mmdet3d/.mim/configs/_base_/default_runtime.py
mmdet3d/.mim/configs/_base_/datasets/kitti-3d-3class.py
mmdet3d/.mim/configs/_base_/datasets/kitti-3d-car.py
mmdet3d/.mim/configs/_base_/datasets/kitti-mono3d.py
mmdet3d/.mim/configs/_base_/datasets/lyft-3d-range100.py
mmdet3d/.mim/configs/_base_/datasets/lyft-3d.py
mmdet3d/.mim/configs/_base_/datasets/nuim-instance.py
mmdet3d/.mim/configs/_base_/datasets/nus-3d.py
mmdet3d/.mim/configs/_base_/datasets/nus-mono3d.py
mmdet3d/.mim/configs/_base_/datasets/s3dis-3d.py
mmdet3d/.mim/configs/_base_/datasets/s3dis-seg.py
mmdet3d/.mim/configs/_base_/datasets/scannet-3d.py
mmdet3d/.mim/configs/_base_/datasets/scannet-seg.py
mmdet3d/.mim/configs/_base_/datasets/semantickitti.py
mmdet3d/.mim/configs/_base_/datasets/sunrgbd-3d.py
mmdet3d/.mim/configs/_base_/datasets/waymoD3-fov-mono3d-3class.py
mmdet3d/.mim/configs/_base_/datasets/waymoD3-mv-mono3d-3class.py
mmdet3d/.mim/configs/_base_/datasets/waymoD5-3d-3class.py
mmdet3d/.mim/configs/_base_/datasets/waymoD5-3d-car.py
mmdet3d/.mim/configs/_base_/datasets/waymoD5-fov-mono3d-3class.py
mmdet3d/.mim/configs/_base_/datasets/waymoD5-mv-mono3d-3class.py
mmdet3d/.mim/configs/_base_/datasets/waymoD5-mv3d-3class.py
mmdet3d/.mim/configs/_base_/models/3dssd.py
mmdet3d/.mim/configs/_base_/models/cascade-mask-rcnn_r50_fpn.py
mmdet3d/.mim/configs/_base_/models/centerpoint_pillar02_second_secfpn_nus.py
mmdet3d/.mim/configs/_base_/models/centerpoint_voxel01_second_secfpn_nus.py
mmdet3d/.mim/configs/_base_/models/cylinder3d.py
mmdet3d/.mim/configs/_base_/models/dgcnn.py
mmdet3d/.mim/configs/_base_/models/fcaf3d.py
mmdet3d/.mim/configs/_base_/models/fcos3d.py
mmdet3d/.mim/configs/_base_/models/groupfree3d.py
mmdet3d/.mim/configs/_base_/models/h3dnet.py
mmdet3d-1.4.0.dist-info/LICENSE
mmdet3d-1.4.0.dist-info/METADATA
mmdet3d-1.4.0.dist-info/WHEEL
mmdet3d-1.4.0.dist-info/top_level.txt
mmdet3d-1.4.0.dist-info/RECORD
