Metadata-Version: 2.1
Name: mmdet3d
Version: 1.4.0
Summary: OpenMMLab's next-generation platformfor general 3D object detection.
Home-page: https://github.com/open-mmlab/mmdetection3d
Author: MMDetection3D Contributors
Author-email: zwwdev@gmail.com
License: Apache License 2.0
Keywords: computer vision,3D object detection
Platform: UNKNOWN
Classifier: Development Status :: 5 - Production/Stable
Classifier: License :: OSI Approved :: Apache Software License
Classifier: Operating System :: OS Independent
Classifier: Programming Language :: Python :: 3
Classifier: Programming Language :: Python :: 3.7
Classifier: Programming Language :: Python :: 3.8
Classifier: Programming Language :: Python :: 3.9
Requires-Dist: lyft-dataset-sdk
Requires-Dist: networkx >=2.5
Requires-Dist: numba
Requires-Dist: numpy
Requires-Dist: nuscenes-devkit
Requires-Dist: open3d
Requires-Dist: plyfile
Requires-Dist: scikit-image
Requires-Dist: tensorboard
Requires-Dist: trimesh
Provides-Extra: all
Requires-Dist: black ==20.8b1 ; extra == 'all'
Requires-Dist: typing-extensions ; extra == 'all'
Requires-Dist: waymo-open-dataset-tf-2-6-0 ; extra == 'all'
Requires-Dist: lyft-dataset-sdk ; extra == 'all'
Requires-Dist: networkx >=2.5 ; extra == 'all'
Requires-Dist: numba ; extra == 'all'
Requires-Dist: numpy ; extra == 'all'
Requires-Dist: nuscenes-devkit ; extra == 'all'
Requires-Dist: open3d ; extra == 'all'
Requires-Dist: plyfile ; extra == 'all'
Requires-Dist: scikit-image ; extra == 'all'
Requires-Dist: tensorboard ; extra == 'all'
Requires-Dist: trimesh ; extra == 'all'
Requires-Dist: codecov ; extra == 'all'
Requires-Dist: flake8 ; extra == 'all'
Requires-Dist: interrogate ; extra == 'all'
Requires-Dist: isort ; extra == 'all'
Requires-Dist: kwarray ; extra == 'all'
Requires-Dist: parameterized ; extra == 'all'
Requires-Dist: pytest ; extra == 'all'
Requires-Dist: pytest-cov ; extra == 'all'
Requires-Dist: pytest-runner ; extra == 'all'
Requires-Dist: ubelt ; extra == 'all'
Requires-Dist: xdoctest >=0.10.0 ; extra == 'all'
Requires-Dist: yapf ; extra == 'all'
Provides-Extra: build
Provides-Extra: mim
Requires-Dist: mmcv <2.2.0,>=2.0.0rc4 ; extra == 'mim'
Requires-Dist: mmdet <3.3.0,>=3.0.0 ; extra == 'mim'
Requires-Dist: mmengine <1.0.0,>=0.7.1 ; extra == 'mim'
Provides-Extra: optional
Requires-Dist: black ==20.8b1 ; extra == 'optional'
Requires-Dist: typing-extensions ; extra == 'optional'
Requires-Dist: waymo-open-dataset-tf-2-6-0 ; extra == 'optional'
Provides-Extra: tests
Requires-Dist: codecov ; extra == 'tests'
Requires-Dist: flake8 ; extra == 'tests'
Requires-Dist: interrogate ; extra == 'tests'
Requires-Dist: isort ; extra == 'tests'
Requires-Dist: kwarray ; extra == 'tests'
Requires-Dist: parameterized ; extra == 'tests'
Requires-Dist: pytest ; extra == 'tests'
Requires-Dist: pytest-cov ; extra == 'tests'
Requires-Dist: pytest-runner ; extra == 'tests'
Requires-Dist: ubelt ; extra == 'tests'
Requires-Dist: xdoctest >=0.10.0 ; extra == 'tests'
Requires-Dist: yapf ; extra == 'tests'
